bidding_common/__init__.py
bidding_common/bidding_common.py
bidding_common/sync_bidding.py
bidding_common-1.0.0.dist-info/LICENSE
bidding_common-1.0.0.dist-info/METADATA
bidding_common-1.0.0.dist-info/WHEEL
bidding_common-1.0.0.dist-info/top_level.txt
bidding_common-1.0.0.dist-info/RECORD
