Metadata-Version: 2.1
Name: bidding-common
Version: 1.0.0
Summary: bidding_tools
Home-page: UNKNOWN
Author: daichaoqing
Author-email: 2625023463@qq.com
License: UNKNOWN
Platform: UNKNOWN
Requires-Python: >=3.6
License-File: LICENSE
